{
  "project_info": {
    "project_number": "115248398984",
    "firebase_url": "https://finalsgp.firebaseio.com",
    "project_id": "finalsgp",
    "storage_bucket": "finalsgp.appspot.com"
  },
  "client": [
    {
      "client_info": {
        "mobilesdk_app_id": "1:115248398984:android:0d3fb667f6794aab57553d",
        "android_client_info": {
          "package_name": "com.example.sgp"
        }
      },
      "oauth_client": [
        {
          "client_id": "115248398984-8oko39ajclerc49a74mceq6arubgvvnc.apps.googleusercontent.com",
          "client_type": 3
        }
      ],
      "api_key": [
        {
          "current_key": "AIzaSyDBshNXUwtRZzbDxwPHYT_6VGOj5nmOnYY"
        }
      ],
      "services": {
        "appinvite_service": {
          "other_platform_oauth_client": [
            {
              "client_id": "115248398984-8oko39ajclerc49a74mceq6arubgvvnc.apps.googleusercontent.com",
              "client_type": 3
            }
          ]
        }
      }
    }
  ],
  "configuration_version": "1"
}